[{"id":"1106152001","district_id":"110615","name":"TEUREUBEH"},{"id":"1106152002","district_id":"110615","name":"BARUEH"},{"id":"1106152003","district_id":"110615","name":"JANTHO"},{"id":"1106152004","district_id":"110615","name":"AWEK (AWEE)"},{"id":"1106152005","district_id":"110615","name":"DATA CUT"},{"id":"1106152006","district_id":"110615","name":"BUENG (BEUNG)"},{"id":"1106152007","district_id":"110615","name":"WEU"},{"id":"1106152008","district_id":"110615","name":"JALIN"},{"id":"1106152009","district_id":"110615","name":"SUKA TANI"},{"id":"1106152010","district_id":"110615","name":"CUCUM"},{"id":"1106152011","district_id":"110615","name":"JANTHO BARU"},{"id":"1106152012","district_id":"110615","name":"JANTHO MAKMUR"},{"id":"1106152013","district_id":"110615","name":"BUKIT MEUSARA"}]