[{"id":"1115012003","district_id":"111501","name":"LAWA BATU"},{"id":"1115012004","district_id":"111501","name":"JOGJA\/JOKJA"},{"id":"1115012019","district_id":"111501","name":"UJONG SIKUNENG"},{"id":"1115012020","district_id":"111501","name":"BLANG MUKO"},{"id":"1115012021","district_id":"111501","name":"PULO IE"},{"id":"1115012022","district_id":"111501","name":"PURWOREJO"},{"id":"1115012023","district_id":"111501","name":"BLANG BARO"},{"id":"1115012024","district_id":"111501","name":"ALUE IE MAMEH"},{"id":"1115012025","district_id":"111501","name":"UJONG PASI"},{"id":"1115012026","district_id":"111501","name":"SIMPANG PEUT"},{"id":"1115012027","district_id":"111501","name":"BLANG TEUNGOH"},{"id":"1115012028","district_id":"111501","name":"UJONG PADANG"},{"id":"1115012029","district_id":"111501","name":"COT KUMBANG"},{"id":"1115012030","district_id":"111501","name":"BLANG BINTANG"},{"id":"1115012031","district_id":"111501","name":"UJONG PATIHAH (UJONG FATIHAH)"},{"id":"1115012032","district_id":"111501","name":"KUTA MAKMUE (KUTA MAKMUR)"},{"id":"1115012033","district_id":"111501","name":"GUNONG REUBO"}]