[{"id":"1206122005","district_id":"120612","name":"KUTATENGAH (KUTA TENGAH)"},{"id":"1206122006","district_id":"120612","name":"TIGAPANCUR (TIGA PANCUR)"},{"id":"1206122007","district_id":"120612","name":"PINTUMBESI (PINTU BESI)"},{"id":"1206122009","district_id":"120612","name":"GAMBER"},{"id":"1206122012","district_id":"120612","name":"SIRUMBIA (SERUMBIA)"},{"id":"1206122014","district_id":"120612","name":"NDOKUMSIROGA (NDOKUM SIROGA)"},{"id":"1206122016","district_id":"120612","name":"LINGGAJULU (LINGGA JULU)"},{"id":"1206122017","district_id":"120612","name":"GAJAH"},{"id":"1206122018","district_id":"120612","name":"LINGGA"},{"id":"1206122019","district_id":"120612","name":"NANGBELAWAN (NANG BELAWAN)"},{"id":"1206122022","district_id":"120612","name":"BEGANDING"},{"id":"1206122024","district_id":"120612","name":"TORONG"},{"id":"1206122025","district_id":"120612","name":"BERASTEPU"},{"id":"1206122026","district_id":"120612","name":"SURBAKTI"},{"id":"1206122028","district_id":"120612","name":"JERAYA"},{"id":"1206122030","district_id":"120612","name":"PERTEGUHEN"},{"id":"1206122035","district_id":"120612","name":"BULANBARU (BULAN BARU)"}]