[{"id":"1207202001","district_id":"120720","name":"TIGA JUHAR"},{"id":"1207202002","district_id":"120720","name":"TANJUNG BANGKU (BAMPU)"},{"id":"1207202003","district_id":"120720","name":"RUMAH RIH"},{"id":"1207202004","district_id":"120720","name":"LIANG MUDA"},{"id":"1207202005","district_id":"120720","name":"DURIAN IV MBELANG (DURIAN EMPAT MBELANG)"},{"id":"1207202006","district_id":"120720","name":"TANAH GARA HULU"},{"id":"1207202007","district_id":"120720","name":"GUNUNG MANUPAK A (GUNUNG MANUMPAK A)"},{"id":"1207202008","district_id":"120720","name":"BAH BAH BUNTU"},{"id":"1207202009","district_id":"120720","name":"TANJUNG MUDA"},{"id":"1207202010","district_id":"120720","name":"TANJUNG RAJA"},{"id":"1207202011","district_id":"120720","name":"KUTA MBELIN"},{"id":"1207202012","district_id":"120720","name":"RUMAH SUMBUL"},{"id":"1207202013","district_id":"120720","name":"RANGGIT-GIT (RANGGITGIT)"},{"id":"1207202014","district_id":"120720","name":"LIANG PEMATANG"},{"id":"1207202015","district_id":"120720","name":"GUNUNG MANUPAK B (GUNUNG MANUMPAK B)"},{"id":"1207202016","district_id":"120720","name":"RUMAH LENGO"},{"id":"1207202017","district_id":"120720","name":"SIPINGGAN"},{"id":"1207202018","district_id":"120720","name":"TANJUNG TIMUR"},{"id":"1207202019","district_id":"120720","name":"DURIAN TINGGUNG (DURIN TINGGUNG)"},{"id":"1207202020","district_id":"120720","name":"SIBUNGA-BUNGA HILIR"}]