[{"id":"1223011001","district_id":"122301","name":"AEK KANOPAN"},{"id":"1223011002","district_id":"122301","name":"AEK KANOPAN TIMUR"},{"id":"1223012003","district_id":"122301","name":"KUALA BERINGIN"},{"id":"1223012004","district_id":"122301","name":"PARPAUDANGAN"},{"id":"1223012005","district_id":"122301","name":"PULO DOGOM"},{"id":"1223012006","district_id":"122301","name":"LONDUT (PERKEBUNAN LONDUT)"},{"id":"1223012007","district_id":"122301","name":"PERKEBUNAN KANOPAN ULU"},{"id":"1223012008","district_id":"122301","name":"PERKEBUNAN MAMBANG\/MEMBANG MUDA"},{"id":"1223012009","district_id":"122301","name":"PERKEBUNAN LABUHAN HAJI"},{"id":"1223012010","district_id":"122301","name":"PERKEBUNAN HANNA"},{"id":"1223012011","district_id":"122301","name":"SONOMARTANI (SONO MARTANI)"},{"id":"1223012012","district_id":"122301","name":"SUKARAME (SUKA RAME)"},{"id":"1223012013","district_id":"122301","name":"SUKARAME BARU (SUKA RAME BARU)"}]