[{"id":"1403112001","district_id":"140311","name":"TANJUNGMEDANG (TANJUNG MEDANG)"},{"id":"1403112002","district_id":"140311","name":"TELUKRHU (TELUK RHU)"},{"id":"1403112003","district_id":"140311","name":"TANJUNGPUNAK (TANJUNG PUNAK)"},{"id":"1403112004","district_id":"140311","name":"KADOR"},{"id":"1403112005","district_id":"140311","name":"TITI AKAR"},{"id":"1403112006","district_id":"140311","name":"HUTAN AYU"},{"id":"1403112007","district_id":"140311","name":"SUKA DAMAI"},{"id":"1403112008","district_id":"140311","name":"PUTERI SEMBILAN"}]