[{"id":"1404011001","district_id":"140401","name":"PULAUKIJANG (PULAU KIJANG)"},{"id":"1404011017","district_id":"140401","name":"METRO"},{"id":"1404011018","district_id":"140401","name":"MADANI"},{"id":"1404012002","district_id":"140401","name":"SANGLAR"},{"id":"1404012003","district_id":"140401","name":"PULAUKECIL (PULAU KECIL)"},{"id":"1404012004","district_id":"140401","name":"SUNGAITERAP (SUNGAI TERAB \/ TERAP)"},{"id":"1404012009","district_id":"140401","name":"SUNGAIUNDAN (SUNGAI UNDAN)"},{"id":"1404012010","district_id":"140401","name":"SEBERANG SANGLAR"},{"id":"1404012011","district_id":"140401","name":"MEKAR SARI"},{"id":"1404012012","district_id":"140401","name":"SEBERANG PULAU KIJANG"},{"id":"1404012013","district_id":"140401","name":"SUNGAIASAM (SUNGAI ASAM)"},{"id":"1404012014","district_id":"140401","name":"PULAURUKU (PULAU RUKU)"},{"id":"1404012019","district_id":"140401","name":"TANJUNGLABUH (TANJUNG LABUH)"},{"id":"1404012020","district_id":"140401","name":"SUNGAIMAHANG (SUNGAI MAHANG)"}]