[{"id":"1605021019","district_id":"160502","name":"MUARA LAKITAN"},{"id":"1605022001","district_id":"160502","name":"TRI ANGGUN JAYA (TRI ANGGUNJAYA)"},{"id":"1605022002","district_id":"160502","name":"SEMANGUS"},{"id":"1605022003","district_id":"160502","name":"ANYAR"},{"id":"1605022004","district_id":"160502","name":"MUARA RENGAS"},{"id":"1605022005","district_id":"160502","name":"SUNGAI PINANG"},{"id":"1605022006","district_id":"160502","name":"SEMETEH"},{"id":"1605022007","district_id":"160502","name":"PRABUMULIH II"},{"id":"1605022008","district_id":"160502","name":"PRABUMULIH I"},{"id":"1605022009","district_id":"160502","name":"LUBUK PANDAN"},{"id":"1605022010","district_id":"160502","name":"PELITA JAYA"},{"id":"1605022011","district_id":"160502","name":"SIDOMULYO (SIDO MULYO)"},{"id":"1605022012","district_id":"160502","name":"MARGA BARU"},{"id":"1605022013","district_id":"160502","name":"PENDINGAN"},{"id":"1605022014","district_id":"160502","name":"BUMI MAKMUR (BUMI MAKMUR JAYA)"},{"id":"1605022015","district_id":"160502","name":"MUKTI KARYA"},{"id":"1605022016","district_id":"160502","name":"HARAPAN MAKMUR"},{"id":"1605022017","district_id":"160502","name":"PIAN RAYA (PIAN JAYA)"},{"id":"1605022018","district_id":"160502","name":"SINDANG LAYA (SINDANG JAYA)"},{"id":"1605022020","district_id":"160502","name":"SEMANGGUS BARU (SEMANGUS BARU)"}]