[{"id":"1811072001","district_id":"181107","name":"BRABASAN"},{"id":"1811072002","district_id":"181107","name":"GEDUNG RAM"},{"id":"1811072003","district_id":"181107","name":"MEKAR SARI"},{"id":"1811072004","district_id":"181107","name":"BUJUNG BURING"},{"id":"1811072005","district_id":"181107","name":"KAGUNGAN DALAM"},{"id":"1811072006","district_id":"181107","name":"TANJUNG SARI"},{"id":"1811072007","district_id":"181107","name":"HARAPAN MUKTI"},{"id":"1811072008","district_id":"181107","name":"SRI TANJUNG"},{"id":"1811072009","district_id":"181107","name":"BANGUN JAYA"},{"id":"1811072010","district_id":"181107","name":"MUARA TENANG"},{"id":"1811072011","district_id":"181107","name":"WIRA JAYA"},{"id":"1811072012","district_id":"181107","name":"SINAR LAGA"},{"id":"1811072013","district_id":"181107","name":"TRI KARYA MULYA"},{"id":"1811072014","district_id":"181107","name":"BERASAN MAKMUR"},{"id":"1811072015","district_id":"181107","name":"MEKAR JAYA"},{"id":"1811072016","district_id":"181107","name":"GEDUNG MULYA"},{"id":"1811072017","district_id":"181107","name":"TANJUNG HARAPAN"},{"id":"1811072018","district_id":"181107","name":"MUARA TENANG TIMUR"},{"id":"1811072019","district_id":"181107","name":"SRIWIJAYA"},{"id":"1811072020","district_id":"181107","name":"MUKTI JAYA"},{"id":"1811072021","district_id":"181107","name":"BUJUNG BURING BARU"}]