[{"id":"7105101004","district_id":"710510","name":"BUYUNGON"},{"id":"7105101005","district_id":"710510","name":"RANOYAPO"},{"id":"7105101006","district_id":"710510","name":"UWURAN I (UWURAN SATU)"},{"id":"7105101007","district_id":"710510","name":"UWURAN II (UWURAN DUA)"},{"id":"7105101008","district_id":"710510","name":"LEWET"},{"id":"7105101010","district_id":"710510","name":"BITUNG"},{"id":"7105102009","district_id":"710510","name":"RANOKETANG TUA"},{"id":"7105102018","district_id":"710510","name":"KILOMETER 3 (KILOMETER TIGA)"}]