[{"id":"7411071001","district_id":"741107","name":"WOITOMBO"},{"id":"7411071002","district_id":"741107","name":"INEBENGGI"},{"id":"7411071004","district_id":"741107","name":"HORODOPI"},{"id":"7411072003","district_id":"741107","name":"NELOMBU"},{"id":"7411072005","district_id":"741107","name":"WATUPUTE"},{"id":"7411072006","district_id":"741107","name":"PUOSU"},{"id":"7411072007","district_id":"741107","name":"ULU MOWEWE"},{"id":"7411072008","district_id":"741107","name":"LAPANGISI"},{"id":"7411072009","district_id":"741107","name":"SABI-SABILA"},{"id":"7411072010","district_id":"741107","name":"LAMBO TUA"}]