[{"id":"121601","regency_id":"1216","name":"PARLILITAN"},{"id":"121602","regency_id":"1216","name":"POLLUNG"},{"id":"121603","regency_id":"1216","name":"BAKTIRAJA (BAKTI RAJA)"},{"id":"121604","regency_id":"1216","name":"PARANGINAN"},{"id":"121605","regency_id":"1216","name":"LINTONG NIHUTA"},{"id":"121606","regency_id":"1216","name":"DOLOK SANGGUL"},{"id":"121607","regency_id":"1216","name":"SIJAMAPOLANG (SIJAMA POLANG)"},{"id":"121608","regency_id":"1216","name":"ONAN GANJANG"},{"id":"121609","regency_id":"1216","name":"PAKKAT"},{"id":"121610","regency_id":"1216","name":"TARABINTANG (TARA BINTANG)"}]