[{"id":"147101","regency_id":"1471","name":"SUKAJADI"},{"id":"147102","regency_id":"1471","name":"PEKANBARU KOTA"},{"id":"147103","regency_id":"1471","name":"SAIL"},{"id":"147104","regency_id":"1471","name":"LIMA PULUH"},{"id":"147105","regency_id":"1471","name":"SENAPELAN"},{"id":"147106","regency_id":"1471","name":"RUMBAI BARAT"},{"id":"147107","regency_id":"1471","name":"BUKIT RAYA"},{"id":"147108","regency_id":"1471","name":"BINAWIDYA"},{"id":"147109","regency_id":"1471","name":"MARPOYAN DAMAI"},{"id":"147110","regency_id":"1471","name":"TENAYAN RAYA"},{"id":"147111","regency_id":"1471","name":"PAYUNG SEKAKI"},{"id":"147112","regency_id":"1471","name":"RUMBAI (RUMBAI PESISIR)"},{"id":"147113","regency_id":"1471","name":"TUAHMADANI"},{"id":"147114","regency_id":"1471","name":"KULIM"},{"id":"147115","regency_id":"1471","name":"RUMBAI TIMUR"}]