[{"id":"1214042001","district_id":"121404","name":"DURU"},{"id":"1214042002","district_id":"121404","name":"TUWASO"},{"id":"1214042003","district_id":"121404","name":"HILIOROMAO (HILIORO MAO)"},{"id":"1214042004","district_id":"121404","name":"EHO"},{"id":"1214042005","district_id":"121404","name":"SIALEMA"},{"id":"1214042006","district_id":"121404","name":"BOWONIFAOSO (BAWONIFAOSO)"},{"id":"1214042007","district_id":"121404","name":"HILIANOMBASELA"},{"id":"1214042008","district_id":"121404","name":"LUMBUI MELAYU"},{"id":"1214042009","district_id":"121404","name":"HILIORODUA TEBOLO (HILIORO DUA TEBOLO)"},{"id":"1214042010","district_id":"121404","name":"TEBOLO MELAYU"},{"id":"1214042021","district_id":"121404","name":"LUMBUI NIAS"},{"id":"1214042022","district_id":"121404","name":"BARUYU SIBOHOU"},{"id":"1214042023","district_id":"121404","name":"SEPAKAT"},{"id":"1214042024","district_id":"121404","name":"TANO MOKINU"},{"id":"1214042025","district_id":"121404","name":"HILIKANA"},{"id":"1214042026","district_id":"121404","name":"HILINIFAESE"},{"id":"1214042027","district_id":"121404","name":"OMEGA"}]