[{"id":"1804232001","district_id":"180423","name":"SUOH"},{"id":"1804232002","district_id":"180423","name":"SRIMULYO"},{"id":"1804232003","district_id":"180423","name":"BANDAR AGUNG"},{"id":"1804232004","district_id":"180423","name":"RINGIN JAYA"},{"id":"1804232005","district_id":"180423","name":"BUMI HANTATAI"},{"id":"1804232006","district_id":"180423","name":"GUNUNGRATU (GUNUNG RATU)"},{"id":"1804232007","district_id":"180423","name":"TANJUNGSARI"},{"id":"1804232008","district_id":"180423","name":"NEGERI JAYA"},{"id":"1804232009","district_id":"180423","name":"TEMBELANG"},{"id":"1804232010","district_id":"180423","name":"TRI MEKAR JAYA"}]