[{"id":"1806011001","district_id":"180601","name":"BAROS"},{"id":"1806011002","district_id":"180601","name":"PASAR MADANG"},{"id":"1806011003","district_id":"180601","name":"KURIPAN"},{"id":"1806012016","district_id":"180601","name":"NEGERI RATU"},{"id":"1806012019","district_id":"180601","name":"PANANGGUNGAN (PENANGGUNGAN)"},{"id":"1806012020","district_id":"180601","name":"TERDANA"},{"id":"1806012021","district_id":"180601","name":"KELUNGU"},{"id":"1806012022","district_id":"180601","name":"PARDASUKA"},{"id":"1806012023","district_id":"180601","name":"TERATAS"},{"id":"1806012024","district_id":"180601","name":"KUSA"},{"id":"1806012025","district_id":"180601","name":"TERBAYA"},{"id":"1806012026","district_id":"180601","name":"KEDAMAIAN"},{"id":"1806012027","district_id":"180601","name":"KOTA AGUNG"},{"id":"1806012039","district_id":"180601","name":"KOTA BATU"},{"id":"1806012040","district_id":"180601","name":"CAMPANG TIGA"},{"id":"1806012041","district_id":"180601","name":"BENTENG JAYA"}]