[{"id":"3303072001","district_id":"330307","name":"KARANGLEWAS"},{"id":"3303072002","district_id":"330307","name":"MUNJUL"},{"id":"3303072003","district_id":"330307","name":"SUMINGKIR"},{"id":"3303072004","district_id":"330307","name":"MERI"},{"id":"3303072005","district_id":"330307","name":"KUTASARI"},{"id":"3303072006","district_id":"330307","name":"KARANGKLESEM"},{"id":"3303072007","district_id":"330307","name":"KARANGREJA"},{"id":"3303072008","district_id":"330307","name":"KARANGAREN"},{"id":"3303072009","district_id":"330307","name":"LIMBANGAN"},{"id":"3303072010","district_id":"330307","name":"CENDANA"},{"id":"3303072011","district_id":"330307","name":"CANDIWULAN"},{"id":"3303072012","district_id":"330307","name":"KARANGCEGAK"},{"id":"3303072013","district_id":"330307","name":"CANDINATA"},{"id":"3303072014","district_id":"330307","name":"KARANGJENGKOL"}]