[{"id":"3507142001","district_id":"350714","name":"SUDIMORO"},{"id":"3507142002","district_id":"350714","name":"KASRI"},{"id":"3507142003","district_id":"350714","name":"BAKALAN"},{"id":"3507142004","district_id":"350714","name":"KREBET"},{"id":"3507142005","district_id":"350714","name":"GADING"},{"id":"3507142006","district_id":"350714","name":"SUKONOLO"},{"id":"3507142007","district_id":"350714","name":"LUMBANGSARI"},{"id":"3507142008","district_id":"350714","name":"WANDANPURO"},{"id":"3507142009","district_id":"350714","name":"SEMPALWADAK"},{"id":"3507142010","district_id":"350714","name":"BULULAWANG"},{"id":"3507142011","district_id":"350714","name":"KREBET SENGGRONG"},{"id":"3507142012","district_id":"350714","name":"KUWOLU"},{"id":"3507142013","district_id":"350714","name":"KASEMBON"},{"id":"3507142014","district_id":"350714","name":"PRINGU"}]