[{"id":"5203202001","district_id":"520320","name":"BATU NAMPAR (BATUNAMPAR)"},{"id":"5203202002","district_id":"520320","name":"SUKARAJA"},{"id":"5203202003","district_id":"520320","name":"JEROWARU"},{"id":"5203202004","district_id":"520320","name":"PEMONGKONG"},{"id":"5203202005","district_id":"520320","name":"SEKAROH"},{"id":"5203202006","district_id":"520320","name":"PANDAN WANGI"},{"id":"5203202007","district_id":"520320","name":"WAKAN"},{"id":"5203202008","district_id":"520320","name":"KWANG RUNDUN"},{"id":"5203202009","district_id":"520320","name":"EKAS BUANA"},{"id":"5203202010","district_id":"520320","name":"SEPAPAN"},{"id":"5203202011","district_id":"520320","name":"SERIWE"},{"id":"5203202012","district_id":"520320","name":"PENE"},{"id":"5203202013","district_id":"520320","name":"BATUNAMPAR SELATAN"},{"id":"5203202014","district_id":"520320","name":"SUKADAMAI"},{"id":"5203202015","district_id":"520320","name":"PARE MAS"}]