[{"id":"6212011012","district_id":"621201","name":"PURUK CAHU"},{"id":"6212011013","district_id":"621201","name":"BERIWIT"},{"id":"6212012001","district_id":"621201","name":"DIRUNG"},{"id":"6212012002","district_id":"621201","name":"MALASAN\/MASALAN"},{"id":"6212012003","district_id":"621201","name":"BATU PUTIH"},{"id":"6212012004","district_id":"621201","name":"MANGKAHUI"},{"id":"6212012005","district_id":"621201","name":"PANU'UT (PANUUT \/ PANAOUT)"},{"id":"6212012006","district_id":"621201","name":"MUARA UNTU"},{"id":"6212012007","district_id":"621201","name":"MUARA JA'AN (MUARA JAAN)"},{"id":"6212012008","district_id":"621201","name":"BAHITOM\/BAHINTOM"},{"id":"6212012009","district_id":"621201","name":"DANAU USUNG"},{"id":"6212012010","district_id":"621201","name":"JANGIN\/JUKING PAJANG"},{"id":"6212012011","district_id":"621201","name":"MUARA SUMPOI"},{"id":"6212012014","district_id":"621201","name":"MUARA BUMBAN\/BAMBAN"},{"id":"6212012015","district_id":"621201","name":"PENYANG"}]