[{"id":"6308051001","district_id":"630805","name":"ANTASARI"},{"id":"6308051002","district_id":"630805","name":"MURUNG SARI"},{"id":"6308051003","district_id":"630805","name":"KEBUN SARI"},{"id":"6308051004","district_id":"630805","name":"PALIWARA"},{"id":"6308051005","district_id":"630805","name":"SEI\/SUNGAI MALANG"},{"id":"6308052006","district_id":"630805","name":"TAPUS"},{"id":"6308052007","district_id":"630805","name":"KANDANG HALANG"},{"id":"6308052008","district_id":"630805","name":"PASAR SENIN"},{"id":"6308052009","district_id":"630805","name":"KOTA RADEN HULU"},{"id":"6308052010","district_id":"630805","name":"TANGGA ULIN HILIR"},{"id":"6308052011","district_id":"630805","name":"TAMBALANGAN"},{"id":"6308052012","district_id":"630805","name":"PALAMPITAN HULU"},{"id":"6308052013","district_id":"630805","name":"HARUS"},{"id":"6308052014","district_id":"630805","name":"PINANGKARA (PINANG KARA)"},{"id":"6308052015","district_id":"630805","name":"SEI\/SUNGAI KARIAS"},{"id":"6308052016","district_id":"630805","name":"TIGARUN"},{"id":"6308052017","district_id":"630805","name":"PINANG HABANG"},{"id":"6308052018","district_id":"630805","name":"HULU PASAR"},{"id":"6308052019","district_id":"630805","name":"KOTA RADEN HILIR"},{"id":"6308052020","district_id":"630805","name":"RANTAWAN"},{"id":"6308052021","district_id":"630805","name":"MUARA TAPUS"},{"id":"6308052022","district_id":"630805","name":"PALAMPITAN HILIR"},{"id":"6308052023","district_id":"630805","name":"HARUSAN"},{"id":"6308052024","district_id":"630805","name":"SEI\/SUNGAI BARING"},{"id":"6308052025","district_id":"630805","name":"KEMBANG KUNING"},{"id":"6308052026","district_id":"630805","name":"DATU KUNING"},{"id":"6308052027","district_id":"630805","name":"TANGGA ULIN HULU"},{"id":"6308052028","district_id":"630805","name":"MAWAR SARI"},{"id":"6308052029","district_id":"630805","name":"DANAU CERMIN (DANAU CARAMIN)"}]