[{"id":"7318191002","district_id":"731819","name":"BENTENG AMBESO (BENTENG DEATA)"},{"id":"7318191004","district_id":"731819","name":"SALUBARANI"},{"id":"7318191012","district_id":"731819","name":"MEBALI"},{"id":"7318192001","district_id":"731819","name":"BUNTU LIMBONG"},{"id":"7318192003","district_id":"731819","name":"SILLANAN"},{"id":"7318192005","district_id":"731819","name":"GANDANGBATU"},{"id":"7318192006","district_id":"731819","name":"KADUAJA"},{"id":"7318192007","district_id":"731819","name":"GARASSIK"},{"id":"7318192008","district_id":"731819","name":"PEMANUKAN"},{"id":"7318192009","district_id":"731819","name":"PERINDINGAN"},{"id":"7318192010","district_id":"731819","name":"BUNTU TABANG"},{"id":"7318192011","district_id":"731819","name":"BETTENG DEATA (BENTENGAMBESO)"}]