[{"id":"7402382001","district_id":"740238","name":"ATODOPI"},{"id":"7402382002","district_id":"740238","name":"MATAHORI"},{"id":"7402382003","district_id":"740238","name":"SAMBAOSU"},{"id":"7402382004","district_id":"740238","name":"MATANGGORAI"},{"id":"7402382005","district_id":"740238","name":"ALOSIKA"},{"id":"7402382006","district_id":"740238","name":"MEKAR JAYA"},{"id":"7402382007","district_id":"740238","name":"LANGGEA"},{"id":"7402382008","district_id":"740238","name":"ALEUTI"},{"id":"7402382009","district_id":"740238","name":"GARUDA"},{"id":"7402382010","district_id":"740238","name":"PADANGGUNI"},{"id":"7402382011","district_id":"740238","name":"PADANG MEKAR"}]