[{"id":"8102182001","district_id":"810218","name":"HOAT"},{"id":"8102182002","district_id":"810218","name":"NGAFAN"},{"id":"8102182003","district_id":"810218","name":"FEER"},{"id":"8102182004","district_id":"810218","name":"REREAN"},{"id":"8102182005","district_id":"810218","name":"NGURKO"},{"id":"8102182006","district_id":"810218","name":"HOKO"},{"id":"8102182007","district_id":"810218","name":"WEDUAR FER (WEDUAR FEER)"},{"id":"8102182008","district_id":"810218","name":"UAT"},{"id":"8102182009","district_id":"810218","name":"NGAN"},{"id":"8102182010","district_id":"810218","name":"WATKIDAT"},{"id":"8102182011","district_id":"810218","name":"OHOILEAN"},{"id":"8102182012","district_id":"810218","name":"WAFOL"},{"id":"8102182013","district_id":"810218","name":"RAHANGIAR"}]