[{"id":"9111022001","district_id":"911102","name":"ARSO KOTA"},{"id":"9111022002","district_id":"911102","name":"WORKWANA"},{"id":"9111022003","district_id":"911102","name":"KWIMI"},{"id":"9111022004","district_id":"911102","name":"UBIYAU"},{"id":"9111022006","district_id":"911102","name":"SAWANAWA"},{"id":"9111022009","district_id":"911102","name":"YUWANAIN"},{"id":"9111022010","district_id":"911102","name":"YANAMAA"},{"id":"9111022011","district_id":"911102","name":"ASYAMAN"},{"id":"9111022012","district_id":"911102","name":"YAMTA"},{"id":"9111022016","district_id":"911102","name":"BAGIA"},{"id":"9111022030","district_id":"911102","name":"SAWABUUN"},{"id":"9111022031","district_id":"911102","name":"BIBIOSI"}]