[{"id":"9304012001","district_id":"930401","name":"YOMOTH"},{"id":"9304012002","district_id":"930401","name":"UWUS"},{"id":"9304012003","district_id":"930401","name":"ASUWETSY"},{"id":"9304012004","district_id":"930401","name":"BISMAM"},{"id":"9304012005","district_id":"930401","name":"BIS AGATS"},{"id":"9304012006","district_id":"930401","name":"PER"},{"id":"9304012007","district_id":"930401","name":"BERITEN"},{"id":"9304012008","district_id":"930401","name":"MBAIT"},{"id":"9304012009","district_id":"930401","name":"BOU"},{"id":"9304012010","district_id":"930401","name":"SAW"},{"id":"9304012011","district_id":"930401","name":"KAYE"},{"id":"9304012012","district_id":"930401","name":"SUWRU"}]