[{"id":"9503292001","district_id":"950329","name":"LELAMBO"},{"id":"9503292002","district_id":"950329","name":"TIBUL (TIMBUL)"},{"id":"9503292003","district_id":"950329","name":"KIKILA"},{"id":"9503292004","district_id":"950329","name":"PALUKAE"},{"id":"9503292005","district_id":"950329","name":"WUBRI"},{"id":"9503292006","district_id":"950329","name":"BARI"},{"id":"9503292007","district_id":"950329","name":"LULUM"},{"id":"9503292008","district_id":"950329","name":"PALEROMON (PALEROMAN)"},{"id":"9503292009","district_id":"950329","name":"LELAMBO DUA (II)"}]