[{"id":"9508012001","district_id":"950801","name":"KENYAM"},{"id":"9508012008","district_id":"950801","name":"KEMALI"},{"id":"9508012012","district_id":"950801","name":"SRALALA"},{"id":"9508012013","district_id":"950801","name":"DELPEL"},{"id":"9508012014","district_id":"950801","name":"YIKE"},{"id":"9508012015","district_id":"950801","name":"YUNAT"},{"id":"9508012016","district_id":"950801","name":"DIM"},{"id":"9508012017","district_id":"950801","name":"ULUNMU"},{"id":"9508012029","district_id":"950801","name":"BOMBAM"}]