[{"id":"9601062001","district_id":"960106","name":"SEGET"},{"id":"9601062004","district_id":"960106","name":"MALABAM (MALABAN)"},{"id":"9601062005","district_id":"960106","name":"PULAU KASIM"},{"id":"9601062010","district_id":"960106","name":"KASIMLE"},{"id":"9601062011","district_id":"960106","name":"WEWENAGU"},{"id":"9601062012","district_id":"960106","name":"WASINGSAN"},{"id":"9601062013","district_id":"960106","name":"KLAYAS"},{"id":"9601062014","district_id":"960106","name":"WAYENKEDE"},{"id":"9601062015","district_id":"960106","name":"MOBI"}]